dask_rasterio/__init__.py
dask_rasterio/read.py
dask_rasterio/write.py
dask_rasterio-0.2.1.dist-info/LICENSE.md
dask_rasterio-0.2.1.dist-info/WHEEL
dask_rasterio-0.2.1.dist-info/METADATA
dask_rasterio-0.2.1.dist-info/RECORD
